[{"invoice_id": 391, "invoice_detail_url": "/invoice/391", "invoice_date": "2023-03-28", "country_of_origin": "China", "seller": "Lamian Communication", "distribution_area": "Bandung", "total_price": 3857000000, "detail": [{"brand": "vivo", "type": "iQOO 7", "price": 27000000, "quantity": "35"}, {"brand": "vivo", "type": "Y20 2021", "price": 2000000, "quantity": "40"}, {"brand": "vivo", "type": "V27e", "price": 63000000, "quantity": "32"}, {"brand": "Realme", "type": "7i", "price": 3000000, "quantity": "23"}, {"brand": "vivo", "type": "X3S", "price": 3000000, "quantity": "27"}, {"brand": "vivo", "type": "X7", "price": 10000000, "quantity": "27"}, {"brand": "vivo", "type": "X70 Pro", "price": 11000000, "quantity": "36"}]}, {"invoice_id": 392, "invoice_detail_url": "/invoice/392", "invoice_date": "2023-03-29", "country_of_origin": "USA", "seller": "Cheeseburger Limited", "distribution_area": "Yogyakarta", "total_price": 1484000000, "detail": [{"brand": "Apple", "type": "iPhone 14 Plus", "price": 19000000, "quantity": "20"}, {"brand": "Apple", "type": "iPhone 12 Pro", "price": 18000000, "quantity": "21"}, {"brand": "Apple", "type": "iPhone 13 Pro Max", "price": 22000000, "quantity": "33"}]}, {"invoice_id": 393, "invoice_detail_url": "/invoice/393", "invoice_date": "2023-03-29", "country_of_origin": "USA", "seller": "Cheeseburger Limited", "distribution_area": "Serang", "total_price": 3456000000, "detail": [{"brand": "Apple", "type": "iPhone XS Max", "price": 11000000, "quantity": "42"}, {"brand": "Apple", "type": "iPhone 12 Pro", "price": 18000000, "quantity": "31"}, {"brand": "Apple", "type": "iPhone XS", "price": 11000000, "quantity": "42"}, {"brand": "Apple", "type": "iPhone 14 Plus", "price": 19000000, "quantity": "28"}, {"brand": "Apple", "type": "iPhone 14 Pro Max", "price": 25000000, "quantity": "25"}, {"brand": "Apple", "type": "iPhone 13 Pro Max", "price": 22000000, "quantity": "21"}, {"brand": "Apple", "type": "iPhone X", "price": 8000000, "quantity": "26"}, {"brand": "Apple", "type": "iPhone 6s", "price": 3000000, "quantity": "49"}]}, {"invoice_id": 394, "invoice_detail_url": "/invoice/394", "invoice_date": "2023-03-30", "country_of_origin": "China", "seller": "Mala Telecom", "distribution_area": "Surabaya", "total_price": 3789000000, "detail": [{"brand": "vivo", "type": "X70 Pro", "price": 11000000, "quantity": "50"}, {"brand": "vivo", "type": "V27e", "price": 63000000, "quantity": "48"}, {"brand": "vivo", "type": "V25e", "price": 5000000, "quantity": "43"}]}, {"invoice_id": 395, "invoice_detail_url": "/invoice/395", "invoice_date": "2023-03-30", "country_of_origin": "China", "seller": "Lamian Communication", "distribution_area": "Surabaya", "total_price": 578000000, "detail": [{"brand": "Realme", "type": "7i", "price": 3000000, "quantity": "32"}, {"brand": "Realme", "type": "C20", "price": 2000000, "quantity": "34"}, {"brand": "Realme", "type": "C21", "price": 2000000, "quantity": "42"}, {"brand": "vivo", "type": "X70 Pro", "price": 11000000, "quantity": "30"}]}, {"invoice_id": 396, "invoice_detail_url": "/invoice/396", "invoice_date": "2023-03-30", "country_of_origin": "China", "seller": "Mala Telecom", "distribution_area": "Serang", "total_price": 2336000000, "detail": [{"brand": "vivo", "type": "X70 Pro", "price": 11000000, "quantity": "26"}, {"brand": "vivo", "type": "Y53", "price": 2000000, "quantity": "32"}, {"brand": "Realme", "type": "GT Neo 5 240W", "price": 13000000, "quantity": "42"}, {"brand": "Realme", "type": "Narzo 30A", "price": 3000000, "quantity": "39"}, {"brand": "vivo", "type": "Y93s", "price": 1000000, "quantity": "39"}, {"brand": "vivo", "type": "iQOO 7", "price": 27000000, "quantity": "43"}, {"brand": "vivo", "type": "V15", "price": 3000000, "quantity": "41"}]}, {"invoice_id": 397, "invoice_detail_url": "/invoice/397", "invoice_date": "2023-03-30", "country_of_origin": "South Korea", "seller": "KimchiTEL", "distribution_area": "Jakarta", "total_price": 1479000000, "detail": [{"brand": "Samsung", "type": "Galaxy M22", "price": 3000000, "quantity": "47"}, {"brand": "Samsung", "type": "Galaxy Alpha", "price": 3000000, "quantity": "34"}, {"brand": "Samsung", "type": "Galaxy Watch Active", "price": 3000000, "quantity": "40"}, {"brand": "Samsung", "type": "Z", "price": 18000000, "quantity": "29"}, {"brand": "Samsung", "type": "Galaxy J2 Prime", "price": 2000000, "quantity": "31"}, {"brand": "Samsung", "type": "Galaxy S20 FE", "price": 8000000, "quantity": "45"}, {"brand": "Samsung", "type": "Galaxy M32", "price": 4000000, "quantity": "43"}]}, {"invoice_id": 398, "invoice_detail_url": "/invoice/398", "invoice_date": "2023-03-30", "country_of_origin": "South Korea", "seller": "BibimbapNET", "distribution_area": "Surabaya", "total_price": 642000000, "detail": [{"brand": "Samsung", "type": "Z1", "price": 14000000, "quantity": "25"}, {"brand": "Samsung", "type": "F250", "price": 1000000, "quantity": "34"}, {"brand": "Samsung", "type": "Galaxy A42 5G", "price": 1000000, "quantity": "28"}, {"brand": "Samsung", "type": "Galaxy A8", "price": 5000000, "quantity": "31"}, {"brand": "Samsung", "type": "Galaxy Alpha", "price": 3000000, "quantity": "25"}]}, {"invoice_id": 399, "invoice_detail_url": "/invoice/399", "invoice_date": "2023-03-30", "country_of_origin": "China", "seller": "Lamian Communication", "distribution_area": "Serang", "total_price": 1302000000, "detail": [{"brand": "vivo", "type": "V25e", "price": 5000000, "quantity": "50"}, {"brand": "vivo", "type": "Y20 2021", "price": 2000000, "quantity": "37"}, {"brand": "vivo", "type": "Y12s", "price": 2000000, "quantity": "44"}, {"brand": "vivo", "type": "Y53", "price": 2000000, "quantity": "40"}, {"brand": "vivo", "type": "iQOO 7", "price": 27000000, "quantity": "30"}]}]